README.md
setup.cfg
setup.py
geomatics_probability/Binomialdistribution.py
geomatics_probability/Gaussiandistribution.py
geomatics_probability/Generaldistribution.py
geomatics_probability/__init__.py
geomatics_probability.egg-info/PKG-INFO
geomatics_probability.egg-info/SOURCES.txt
geomatics_probability.egg-info/dependency_links.txt
geomatics_probability.egg-info/not-zip-safe
geomatics_probability.egg-info/top_level.txt